setup.py
taar_loader/__init__.py
taar_loader/filters.py
taar_loader/insert_record.py
taar_loader/taar_dynamo.py
taar_loader/test.py
taar_loader.egg-info/PKG-INFO
taar_loader.egg-info/SOURCES.txt
taar_loader.egg-info/dependency_links.txt
taar_loader.egg-info/top_level.txt