Metadata-Version: 1.0
Name: taar-loader
Version: 1.0
Summary: Migration tool to move data from Telemetry S3 buckets over to DynamoDB
Home-page: UNKNOWN
Author: Victor Ng
Author-email: vng@mozilla.com
License: MPL 2.0
Platform: UNKNOWN
